integ/miur-python-shebang.py
integ/miur-shell-aliases.sh
integ/miur-shell-sync-cwd.zsh
miur/__init__.py
miur/__main__.py
miur/_pkg.py
miur/app.py
miur/cli.py
miur/curses_ext.py
miur/iomgr.py
miur/keymap.py
miur/loop_asyncio.py
miur/loop_selectors.py
miur/miur.py
miur/alg/flowratio.py
miur/alg/orderview.py
miur/alg/scrollwnd.py
miur/entity/__init__.py
miur/entity/error.py
miur/entity/fsentry.py
miur/entity/mpdnode.py
miur/entity/objaction.py
miur/entity/pacmannode.py
miur/entity/psnode.py
miur/entity/rootnode.py
miur/entity/text.py
miur/entity/unicodenode.py
miur/entity/webnode.py
miur/entity/base/__init__.py
miur/entity/base/action.py
miur/entity/base/autodiscover.py
miur/entity/base/golden.py
miur/entity/base/loci.py
miur/entity/base/traits.py
miur/integ/RENAME
miur/integ/__init__.py
miur/integ/any_exe.py
miur/integ/any_spawn.py
miur/integ/aura.py
miur/integ/jupyter.py
miur/integ/nvim.py
miur/integ/ranger.py
miur/integ/shell.py
miur/integ/xclip.py
miur/ui/__init__.py
miur/ui/_live.py
miur/ui/colorscheme.py
miur/ui/item.py
miur/ui/itemcolor.py
miur/ui/itemparts.py
miur/ui/navi.py
miur/ui/navihistory.py
miur/ui/panel.py
miur/ui/panelcfg.py
miur/ui/rect.py
miur/ui/root.py
miur/ui/view.py
miur/ui/vlst.py
miur/ui/vlst_base.py
miur/ui/vlst_redraw.py
miur/ui/vlst_stepby.py
miur/ui/render/RENAME.nou
miur/ui/render/__init__.py
miur/ui/render/glfw_imgui.py
miur/ui/render/pyqtgr_numpy.py
miur/ui/render/qt6gl.py
miur/ui/render/qt6qml.py
miur/ui/render/qt6wg.py
miur/ui/render/sdl3gl_imgui.py
miur/ui/render/vispy2d.py
miur/ui/render/qml/qmldir
miur/ui/render/qml/qt6qml.qml
miur/util/__init__.py
miur/util/devenv.py
miur/util/envlevel.py
miur/util/exchook.py
miur/util/jupyter.py
miur/util/logger.py
miur/util/pidfile.py
miur/util/sighandler.py
miur/util/termansi.py
miur-0.571.20250319.dist-info/METADATA
miur-0.571.20250319.dist-info/WHEEL
miur-0.571.20250319.dist-info/RECORD
