Metadata-Version: 2.4
Name: miur
Version: 0.571.20250319
Summary: Modern Interface for Uniform Reconnaissance
Project-URL: Homepage, https://github.com/miur/miur
Project-URL: GitHub, https://github.com/miur/miur
Project-URL: Source, https://github.com/miur/miur
Project-URL: Issues, https://github.com/miur/miur/issues
Project-URL: Documentation, https://github.com/miur/miur/wiki
Project-URL: Changelog, https://github.com/miur/miur/blob/main/README.rst
Project-URL: Chat, https://github.com/miur/miur/discussions
Project-URL: ReleaseNotes, https://github.com/miur/miur/releases
Project-URL: Download, https://github.com/miur/miur/releases
Project-URL: PyPI, https://pypi.org/project/miur/
Author-email: Dmytro Kolomoiets <amerlyq+code@gmail.com>
License-Expression: GPL-3.0-only
Classifier: License :: OSI Approved :: GNU General Public License v3 (GPLv3)
Classifier: Operating System :: POSIX :: Linux
Classifier: Programming Language :: Python :: 3
Classifier: Typing :: Typed
Requires-Python: >=3.12
Requires-Dist: pygments
Requires-Dist: python-mpd2
Requires-Dist: ranger-fm
Provides-Extra: all
Requires-Dist: beautifulsoup4; extra == 'all'
Requires-Dist: glfw; extra == 'all'
Requires-Dist: imgui-bundle; extra == 'all'
Requires-Dist: lxml; extra == 'all'
Requires-Dist: pyqt6; extra == 'all'
Requires-Dist: pyqtgraph; extra == 'all'
Requires-Dist: pysdl3; extra == 'all'
Requires-Dist: requests; extra == 'all'
Requires-Dist: vispy; extra == 'all'
Provides-Extra: default
Requires-Dist: beautifulsoup4; extra == 'default'
Requires-Dist: lxml; extra == 'default'
Requires-Dist: requests; extra == 'default'
Provides-Extra: demo
Requires-Dist: glfw; extra == 'demo'
Requires-Dist: imgui-bundle; extra == 'demo'
Requires-Dist: pyqt6; extra == 'demo'
Requires-Dist: pyqtgraph; extra == 'demo'
Requires-Dist: pysdl3; extra == 'demo'
Requires-Dist: vispy; extra == 'demo'
Provides-Extra: dev
Requires-Dist: black; extra == 'dev'
Requires-Dist: isort; extra == 'dev'
Requires-Dist: jupyter-console; extra == 'dev'
Requires-Dist: mypy; extra == 'dev'
Requires-Dist: pip-tools; extra == 'dev'
Requires-Dist: pylint; extra == 'dev'
Requires-Dist: pylint-venv; extra == 'dev'
Provides-Extra: web
Requires-Dist: beautifulsoup4; extra == 'web'
Requires-Dist: lxml; extra == 'web'
Requires-Dist: requests; extra == 'web'
